{
  "draw_number": 6913,
  "target_draw_number": 6913,
  "date": "20260204",
  "method": "low_sum_specialist",
  "predictions": [
    {
      "time": "2026-02-04T18:17:34.729328+00:00",
      "time_jst": "03:17",
      "method": "low_sum_specialist",
      "top_predictions": [
        {
          "rank": 1,
          "number": "2230",
          "score": 100.0
        },
        {
          "rank": 2,
          "number": "2212",
          "score": 99.12
        },
        {
          "rank": 3,
          "number": "2303",
          "score": 98.25
        },
        {
          "rank": 4,
          "number": "2222",
          "score": 97.37
        },
        {
          "rank": 5,
          "number": "2421",
          "score": 96.49
        },
        {
          "rank": 6,
          "number": "2511",
          "score": 95.61
        },
        {
          "rank": 7,
          "number": "2071",
          "score": 94.74
        },
        {
          "rank": 8,
          "number": "2044",
          "score": 93.86
        },
        {
          "rank": 9,
          "number": "2161",
          "score": 92.98
        },
        {
          "rank": 10,
          "number": "2008",
          "score": 92.11
        },
        {
          "rank": 11,
          "number": "2621",
          "score": 91.23
        },
        {
          "rank": 12,
          "number": "2045",
          "score": 90.35
        },
        {
          "rank": 13,
          "number": "2414",
          "score": 89.47
        },
        {
          "rank": 14,
          "number": "2262",
          "score": 88.6
        },
        {
          "rank": 15,
          "number": "2424",
          "score": 87.72
        },
        {
          "rank": 16,
          "number": "0000",
          "score": 86.84
        },
        {
          "rank": 17,
          "number": "1213",
          "score": 85.96
        },
        {
          "rank": 18,
          "number": "1223",
          "score": 85.09
        },
        {
          "rank": 19,
          "number": "1313",
          "score": 84.21
        },
        {
          "rank": 20,
          "number": "1151",
          "score": 83.33
        }
      ],
      "metadata": {
        "limit": 200,
        "total_predictions": 114
      }
    },
    {
      "time": "2026-02-04T19:42:43.055644+00:00",
      "time_jst": "04:42",
      "method": "low_sum_specialist",
      "top_predictions": [
        {
          "rank": 1,
          "number": "2212",
          "score": 100.0
        },
        {
          "rank": 2,
          "number": "2032",
          "score": 99.13
        },
        {
          "rank": 3,
          "number": "2060",
          "score": 98.26
        },
        {
          "rank": 4,
          "number": "2222",
          "score": 97.39
        },
        {
          "rank": 5,
          "number": "2601",
          "score": 96.52
        },
        {
          "rank": 6,
          "number": "2322",
          "score": 95.65
        },
        {
          "rank": 7,
          "number": "2115",
          "score": 94.78
        },
        {
          "rank": 8,
          "number": "2340",
          "score": 93.91
        },
        {
          "rank": 9,
          "number": "2224",
          "score": 93.04
        },
        {
          "rank": 10,
          "number": "2504",
          "score": 92.17
        },
        {
          "rank": 11,
          "number": "2522",
          "score": 91.3
        },
        {
          "rank": 12,
          "number": "0000",
          "score": 90.43
        },
        {
          "rank": 13,
          "number": "1321",
          "score": 89.57
        },
        {
          "rank": 14,
          "number": "1114",
          "score": 88.7
        },
        {
          "rank": 15,
          "number": "1051",
          "score": 87.83
        },
        {
          "rank": 16,
          "number": "1034",
          "score": 86.96
        },
        {
          "rank": 17,
          "number": "1520",
          "score": 86.09
        },
        {
          "rank": 18,
          "number": "1511",
          "score": 85.22
        },
        {
          "rank": 19,
          "number": "1601",
          "score": 84.35
        },
        {
          "rank": 20,
          "number": "1322",
          "score": 83.48
        }
      ],
      "metadata": {
        "limit": 200,
        "total_predictions": 115
      }
    },
    {
      "time": "2026-02-04T21:07:28.096630+00:00",
      "time_jst": "06:07",
      "method": "low_sum_specialist",
      "top_predictions": [
        {
          "rank": 1,
          "number": "2221",
          "score": 100.0
        },
        {
          "rank": 2,
          "number": "2023",
          "score": 99.12
        },
        {
          "rank": 3,
          "number": "2131",
          "score": 98.25
        },
        {
          "rank": 4,
          "number": "2123",
          "score": 97.37
        },
        {
          "rank": 5,
          "number": "2222",
          "score": 96.49
        },
        {
          "rank": 6,
          "number": "2205",
          "score": 95.61
        },
        {
          "rank": 7,
          "number": "2700",
          "score": 94.74
        },
        {
          "rank": 8,
          "number": "2214",
          "score": 93.86
        },
        {
          "rank": 9,
          "number": "2143",
          "score": 92.98
        },
        {
          "rank": 10,
          "number": "2422",
          "score": 92.11
        },
        {
          "rank": 11,
          "number": "2180",
          "score": 91.23
        },
        {
          "rank": 12,
          "number": "2046",
          "score": 90.35
        },
        {
          "rank": 13,
          "number": "2244",
          "score": 89.47
        },
        {
          "rank": 14,
          "number": "2343",
          "score": 88.6
        },
        {
          "rank": 15,
          "number": "0000",
          "score": 87.72
        },
        {
          "rank": 16,
          "number": "1105",
          "score": 86.84
        },
        {
          "rank": 17,
          "number": "1060",
          "score": 85.96
        },
        {
          "rank": 18,
          "number": "1141",
          "score": 85.09
        },
        {
          "rank": 19,
          "number": "1151",
          "score": 84.21
        },
        {
          "rank": 20,
          "number": "1331",
          "score": 83.33
        }
      ],
      "metadata": {
        "limit": 200,
        "total_predictions": 114
      }
    }
  ],
  "last_updated": "2026-02-04T21:07:28.096630+00:00",
  "prediction_count": 3
}