{
  "draw_number": 6957,
  "target_draw_number": 6957,
  "date": "20260407",
  "method": "low_sum_specialist",
  "predictions": [
    {
      "time": "2026-04-07T17:00:25.144000+00:00",
      "time_jst": "02:00",
      "method": "low_sum_specialist",
      "top_predictions": [
        {
          "rank": 1,
          "number": "0000",
          "score": 100.0
        },
        {
          "rank": 2,
          "number": "1150",
          "score": 99.14
        },
        {
          "rank": 3,
          "number": "1222",
          "score": 98.28
        },
        {
          "rank": 4,
          "number": "1411",
          "score": 97.41
        },
        {
          "rank": 5,
          "number": "1412",
          "score": 96.55
        },
        {
          "rank": 6,
          "number": "1304",
          "score": 95.69
        },
        {
          "rank": 7,
          "number": "1115",
          "score": 94.83
        },
        {
          "rank": 8,
          "number": "1313",
          "score": 93.97
        },
        {
          "rank": 9,
          "number": "1053",
          "score": 93.1
        },
        {
          "rank": 10,
          "number": "1233",
          "score": 92.24
        },
        {
          "rank": 11,
          "number": "1521",
          "score": 91.38
        },
        {
          "rank": 12,
          "number": "1134",
          "score": 90.52
        },
        {
          "rank": 13,
          "number": "1161",
          "score": 89.66
        },
        {
          "rank": 14,
          "number": "1315",
          "score": 88.79
        },
        {
          "rank": 15,
          "number": "1108",
          "score": 87.93
        },
        {
          "rank": 16,
          "number": "1019",
          "score": 87.07
        },
        {
          "rank": 17,
          "number": "1262",
          "score": 86.21
        },
        {
          "rank": 18,
          "number": "1145",
          "score": 85.34
        },
        {
          "rank": 19,
          "number": "1424",
          "score": 84.48
        },
        {
          "rank": 20,
          "number": "1434",
          "score": 83.62
        }
      ],
      "metadata": {
        "limit": 200,
        "total_predictions": 116
      }
    },
    {
      "time": "2026-04-07T18:29:47.001365+00:00",
      "time_jst": "03:29",
      "method": "low_sum_specialist",
      "top_predictions": [
        {
          "rank": 1,
          "number": "0000",
          "score": 100.0
        },
        {
          "rank": 2,
          "number": "1051",
          "score": 99.13
        },
        {
          "rank": 3,
          "number": "1222",
          "score": 98.26
        },
        {
          "rank": 4,
          "number": "1141",
          "score": 97.39
        },
        {
          "rank": 5,
          "number": "1304",
          "score": 96.52
        },
        {
          "rank": 6,
          "number": "1511",
          "score": 95.65
        },
        {
          "rank": 7,
          "number": "1070",
          "score": 94.78
        },
        {
          "rank": 8,
          "number": "1331",
          "score": 93.91
        },
        {
          "rank": 9,
          "number": "1314",
          "score": 93.04
        },
        {
          "rank": 10,
          "number": "1107",
          "score": 92.17
        },
        {
          "rank": 11,
          "number": "1116",
          "score": 91.3
        },
        {
          "rank": 12,
          "number": "1261",
          "score": 90.43
        },
        {
          "rank": 13,
          "number": "1018",
          "score": 89.57
        },
        {
          "rank": 14,
          "number": "1352",
          "score": 88.7
        },
        {
          "rank": 15,
          "number": "1424",
          "score": 87.83
        },
        {
          "rank": 16,
          "number": "1461",
          "score": 86.96
        },
        {
          "rank": 17,
          "number": "2050",
          "score": 86.09
        },
        {
          "rank": 18,
          "number": "2240",
          "score": 85.22
        },
        {
          "rank": 19,
          "number": "2411",
          "score": 84.35
        },
        {
          "rank": 20,
          "number": "2321",
          "score": 83.48
        }
      ],
      "metadata": {
        "limit": 200,
        "total_predictions": 115
      }
    },
    {
      "time": "2026-04-07T19:40:41.853672+00:00",
      "time_jst": "04:40",
      "method": "low_sum_specialist",
      "top_predictions": [
        {
          "rank": 1,
          "number": "0000",
          "score": 100.0
        },
        {
          "rank": 2,
          "number": "1510",
          "score": 99.13
        },
        {
          "rank": 3,
          "number": "1141",
          "score": 98.26
        },
        {
          "rank": 4,
          "number": "1421",
          "score": 97.39
        },
        {
          "rank": 5,
          "number": "1403",
          "score": 96.52
        },
        {
          "rank": 6,
          "number": "1016",
          "score": 95.65
        },
        {
          "rank": 7,
          "number": "1115",
          "score": 94.78
        },
        {
          "rank": 8,
          "number": "1404",
          "score": 93.91
        },
        {
          "rank": 9,
          "number": "1215",
          "score": 93.04
        },
        {
          "rank": 10,
          "number": "1233",
          "score": 92.17
        },
        {
          "rank": 11,
          "number": "1441",
          "score": 91.3
        },
        {
          "rank": 12,
          "number": "1306",
          "score": 90.43
        },
        {
          "rank": 13,
          "number": "1523",
          "score": 89.57
        },
        {
          "rank": 14,
          "number": "1226",
          "score": 88.7
        },
        {
          "rank": 15,
          "number": "1451",
          "score": 87.83
        },
        {
          "rank": 16,
          "number": "1640",
          "score": 86.96
        },
        {
          "rank": 17,
          "number": "1443",
          "score": 86.09
        },
        {
          "rank": 18,
          "number": "2041",
          "score": 85.22
        },
        {
          "rank": 19,
          "number": "2212",
          "score": 84.35
        },
        {
          "rank": 20,
          "number": "2312",
          "score": 83.48
        }
      ],
      "metadata": {
        "limit": 200,
        "total_predictions": 115
      }
    }
  ],
  "last_updated": "2026-04-07T19:40:41.853672+00:00",
  "prediction_count": 3
}