{
  "draw_number": 6962,
  "target_draw_number": 6962,
  "date": "20260414",
  "method": "low_sum_specialist",
  "predictions": [
    {
      "time": "2026-04-14T17:01:43.299070+00:00",
      "time_jst": "02:01",
      "method": "low_sum_specialist",
      "top_predictions": [
        {
          "rank": 1,
          "number": "0000",
          "score": 100.0
        },
        {
          "rank": 2,
          "number": "0340",
          "score": 99.13
        },
        {
          "rank": 3,
          "number": "0241",
          "score": 98.26
        },
        {
          "rank": 4,
          "number": "0331",
          "score": 97.39
        },
        {
          "rank": 5,
          "number": "0205",
          "score": 96.52
        },
        {
          "rank": 6,
          "number": "0070",
          "score": 95.65
        },
        {
          "rank": 7,
          "number": "0620",
          "score": 94.78
        },
        {
          "rank": 8,
          "number": "0134",
          "score": 93.91
        },
        {
          "rank": 9,
          "number": "0107",
          "score": 93.04
        },
        {
          "rank": 10,
          "number": "0080",
          "score": 92.17
        },
        {
          "rank": 11,
          "number": "0513",
          "score": 91.3
        },
        {
          "rank": 12,
          "number": "0504",
          "score": 90.43
        },
        {
          "rank": 13,
          "number": "0243",
          "score": 89.57
        },
        {
          "rank": 14,
          "number": "0414",
          "score": 88.7
        },
        {
          "rank": 15,
          "number": "0108",
          "score": 87.83
        },
        {
          "rank": 16,
          "number": "0613",
          "score": 86.96
        },
        {
          "rank": 17,
          "number": "0622",
          "score": 86.09
        },
        {
          "rank": 18,
          "number": "0506",
          "score": 85.22
        },
        {
          "rank": 19,
          "number": "0353",
          "score": 84.35
        },
        {
          "rank": 20,
          "number": "0317",
          "score": 83.48
        }
      ],
      "metadata": {
        "limit": 200,
        "total_predictions": 115
      }
    },
    {
      "time": "2026-04-14T18:22:52.333393+00:00",
      "time_jst": "03:22",
      "method": "low_sum_specialist",
      "top_predictions": [
        {
          "rank": 1,
          "number": "0000",
          "score": 100.0
        },
        {
          "rank": 2,
          "number": "0511",
          "score": 99.12
        },
        {
          "rank": 3,
          "number": "0133",
          "score": 98.25
        },
        {
          "rank": 4,
          "number": "0232",
          "score": 97.37
        },
        {
          "rank": 5,
          "number": "0070",
          "score": 96.49
        },
        {
          "rank": 6,
          "number": "0044",
          "score": 95.61
        },
        {
          "rank": 7,
          "number": "0800",
          "score": 94.74
        },
        {
          "rank": 8,
          "number": "0270",
          "score": 93.86
        },
        {
          "rank": 9,
          "number": "0504",
          "score": 92.98
        },
        {
          "rank": 10,
          "number": "0522",
          "score": 92.11
        },
        {
          "rank": 11,
          "number": "0532",
          "score": 91.23
        },
        {
          "rank": 12,
          "number": "0631",
          "score": 90.35
        },
        {
          "rank": 13,
          "number": "0505",
          "score": 89.47
        },
        {
          "rank": 14,
          "number": "0290",
          "score": 88.6
        },
        {
          "rank": 15,
          "number": "0605",
          "score": 87.72
        },
        {
          "rank": 16,
          "number": "0353",
          "score": 86.84
        },
        {
          "rank": 17,
          "number": "0740",
          "score": 85.96
        },
        {
          "rank": 18,
          "number": "0255",
          "score": 85.09
        },
        {
          "rank": 19,
          "number": "0660",
          "score": 84.21
        },
        {
          "rank": 20,
          "number": "2005",
          "score": 83.33
        }
      ],
      "metadata": {
        "limit": 200,
        "total_predictions": 114
      }
    },
    {
      "time": "2026-04-14T19:47:21.456799+00:00",
      "time_jst": "04:47",
      "method": "low_sum_specialist",
      "top_predictions": [
        {
          "rank": 1,
          "number": "0000",
          "score": 100.0
        },
        {
          "rank": 2,
          "number": "0241",
          "score": 99.12
        },
        {
          "rank": 3,
          "number": "0016",
          "score": 98.23
        },
        {
          "rank": 4,
          "number": "0700",
          "score": 97.35
        },
        {
          "rank": 5,
          "number": "0503",
          "score": 96.46
        },
        {
          "rank": 6,
          "number": "0080",
          "score": 95.58
        },
        {
          "rank": 7,
          "number": "0323",
          "score": 94.69
        },
        {
          "rank": 8,
          "number": "0225",
          "score": 93.81
        },
        {
          "rank": 9,
          "number": "0531",
          "score": 92.92
        },
        {
          "rank": 10,
          "number": "0432",
          "score": 92.04
        },
        {
          "rank": 11,
          "number": "0640",
          "score": 91.15
        },
        {
          "rank": 12,
          "number": "0325",
          "score": 90.27
        },
        {
          "rank": 13,
          "number": "0226",
          "score": 89.38
        },
        {
          "rank": 14,
          "number": "0118",
          "score": 88.5
        },
        {
          "rank": 15,
          "number": "0650",
          "score": 87.61
        },
        {
          "rank": 16,
          "number": "0416",
          "score": 86.73
        },
        {
          "rank": 17,
          "number": "0434",
          "score": 85.84
        },
        {
          "rank": 18,
          "number": "0362",
          "score": 84.96
        },
        {
          "rank": 19,
          "number": "0317",
          "score": 84.07
        },
        {
          "rank": 20,
          "number": "0471",
          "score": 83.19
        }
      ],
      "metadata": {
        "limit": 200,
        "total_predictions": 113
      }
    },
    {
      "time": "2026-04-14T21:03:47.603309+00:00",
      "time_jst": "06:03",
      "method": "low_sum_specialist",
      "top_predictions": [
        {
          "rank": 1,
          "number": "0000",
          "score": 100.0
        },
        {
          "rank": 2,
          "number": "0016",
          "score": 99.12
        },
        {
          "rank": 3,
          "number": "0151",
          "score": 98.25
        },
        {
          "rank": 4,
          "number": "0700",
          "score": 97.37
        },
        {
          "rank": 5,
          "number": "0422",
          "score": 96.49
        },
        {
          "rank": 6,
          "number": "0161",
          "score": 95.61
        },
        {
          "rank": 7,
          "number": "0035",
          "score": 94.74
        },
        {
          "rank": 8,
          "number": "0071",
          "score": 93.86
        },
        {
          "rank": 9,
          "number": "0324",
          "score": 92.98
        },
        {
          "rank": 10,
          "number": "0405",
          "score": 92.11
        },
        {
          "rank": 11,
          "number": "0117",
          "score": 91.23
        },
        {
          "rank": 12,
          "number": "0640",
          "score": 90.35
        },
        {
          "rank": 13,
          "number": "0235",
          "score": 89.47
        },
        {
          "rank": 14,
          "number": "0244",
          "score": 88.6
        },
        {
          "rank": 15,
          "number": "0334",
          "score": 87.72
        },
        {
          "rank": 16,
          "number": "0271",
          "score": 86.84
        },
        {
          "rank": 17,
          "number": "0055",
          "score": 85.96
        },
        {
          "rank": 18,
          "number": "0281",
          "score": 85.09
        },
        {
          "rank": 19,
          "number": "0506",
          "score": 84.21
        },
        {
          "rank": 20,
          "number": "0471",
          "score": 83.33
        }
      ],
      "metadata": {
        "limit": 200,
        "total_predictions": 114
      }
    },
    {
      "time": "2026-04-14T22:23:29.463847+00:00",
      "time_jst": "07:23",
      "method": "low_sum_specialist",
      "top_predictions": [
        {
          "rank": 1,
          "number": "0000",
          "score": 100.0
        },
        {
          "rank": 2,
          "number": "0502",
          "score": 99.13
        },
        {
          "rank": 3,
          "number": "0160",
          "score": 98.26
        },
        {
          "rank": 4,
          "number": "0700",
          "score": 97.39
        },
        {
          "rank": 5,
          "number": "0224",
          "score": 96.52
        },
        {
          "rank": 6,
          "number": "0323",
          "score": 95.65
        },
        {
          "rank": 7,
          "number": "0017",
          "score": 94.78
        },
        {
          "rank": 8,
          "number": "0603",
          "score": 93.91
        },
        {
          "rank": 9,
          "number": "0333",
          "score": 93.04
        },
        {
          "rank": 10,
          "number": "0550",
          "score": 92.17
        },
        {
          "rank": 11,
          "number": "0246",
          "score": 91.3
        },
        {
          "rank": 12,
          "number": "0831",
          "score": 90.43
        },
        {
          "rank": 13,
          "number": "0156",
          "score": 89.57
        },
        {
          "rank": 14,
          "number": "2311",
          "score": 88.7
        },
        {
          "rank": 15,
          "number": "2122",
          "score": 87.83
        },
        {
          "rank": 16,
          "number": "2321",
          "score": 86.96
        },
        {
          "rank": 17,
          "number": "2510",
          "score": 86.09
        },
        {
          "rank": 18,
          "number": "2222",
          "score": 85.22
        },
        {
          "rank": 19,
          "number": "2006",
          "score": 84.35
        },
        {
          "rank": 20,
          "number": "2502",
          "score": 83.48
        }
      ],
      "metadata": {
        "limit": 200,
        "total_predictions": 115
      }
    },
    {
      "time": "2026-04-14T23:58:17.735369+00:00",
      "time_jst": "08:58",
      "method": "low_sum_specialist",
      "top_predictions": [
        {
          "rank": 1,
          "number": "0000",
          "score": 100.0
        },
        {
          "rank": 2,
          "number": "0106",
          "score": 99.13
        },
        {
          "rank": 3,
          "number": "0322",
          "score": 98.26
        },
        {
          "rank": 4,
          "number": "0214",
          "score": 97.39
        },
        {
          "rank": 5,
          "number": "0115",
          "score": 96.52
        },
        {
          "rank": 6,
          "number": "0133",
          "score": 95.65
        },
        {
          "rank": 7,
          "number": "0008",
          "score": 94.78
        },
        {
          "rank": 8,
          "number": "0440",
          "score": 93.91
        },
        {
          "rank": 9,
          "number": "0530",
          "score": 93.04
        },
        {
          "rank": 10,
          "number": "0701",
          "score": 92.17
        },
        {
          "rank": 11,
          "number": "0018",
          "score": 91.3
        },
        {
          "rank": 12,
          "number": "0270",
          "score": 90.43
        },
        {
          "rank": 13,
          "number": "0450",
          "score": 89.57
        },
        {
          "rank": 14,
          "number": "0441",
          "score": 88.7
        },
        {
          "rank": 15,
          "number": "0604",
          "score": 87.83
        },
        {
          "rank": 16,
          "number": "0721",
          "score": 86.96
        },
        {
          "rank": 17,
          "number": "0560",
          "score": 86.09
        },
        {
          "rank": 18,
          "number": "0066",
          "score": 85.22
        },
        {
          "rank": 19,
          "number": "2122",
          "score": 84.35
        },
        {
          "rank": 20,
          "number": "2033",
          "score": 83.48
        }
      ],
      "metadata": {
        "limit": 200,
        "total_predictions": 115
      }
    }
  ],
  "last_updated": "2026-04-14T23:58:17.735369+00:00",
  "prediction_count": 6
}