{
  "draw_number": 6950,
  "target_draw_number": 6950,
  "date": "20260329",
  "method": "even_odd_pattern",
  "predictions": [
    {
      "time": "2026-03-29T05:36:18.489950+00:00",
      "time_jst": "14:36",
      "method": "even_odd_pattern",
      "top_predictions": [
        {
          "rank": 1,
          "number": "9999",
          "score": 100.0
        },
        {
          "rank": 2,
          "number": "9599",
          "score": 99.47
        },
        {
          "rank": 3,
          "number": "9595",
          "score": 98.95
        },
        {
          "rank": 4,
          "number": "9555",
          "score": 98.42
        },
        {
          "rank": 5,
          "number": "4444",
          "score": 97.89
        },
        {
          "rank": 6,
          "number": "9997",
          "score": 97.37
        },
        {
          "rank": 7,
          "number": "5555",
          "score": 96.84
        },
        {
          "rank": 8,
          "number": "4446",
          "score": 96.32
        },
        {
          "rank": 9,
          "number": "5799",
          "score": 95.79
        },
        {
          "rank": 10,
          "number": "4664",
          "score": 95.26
        },
        {
          "rank": 11,
          "number": "9557",
          "score": 94.74
        },
        {
          "rank": 12,
          "number": "4666",
          "score": 94.21
        },
        {
          "rank": 13,
          "number": "8444",
          "score": 93.68
        },
        {
          "rank": 14,
          "number": "9991",
          "score": 93.16
        },
        {
          "rank": 15,
          "number": "5755",
          "score": 92.63
        },
        {
          "rank": 16,
          "number": "4648",
          "score": 92.11
        },
        {
          "rank": 17,
          "number": "6666",
          "score": 91.58
        },
        {
          "rank": 18,
          "number": "7997",
          "score": 91.05
        },
        {
          "rank": 19,
          "number": "5199",
          "score": 90.53
        },
        {
          "rank": 20,
          "number": "8646",
          "score": 90.0
        }
      ],
      "metadata": {
        "limit": 200,
        "total_predictions": 190
      }
    },
    {
      "time": "2026-03-29T05:45:42.755287+00:00",
      "time_jst": "14:45",
      "method": "even_odd_pattern",
      "top_predictions": [
        {
          "rank": 1,
          "number": "9999",
          "score": 100.0
        },
        {
          "rank": 2,
          "number": "9959",
          "score": 99.47
        },
        {
          "rank": 3,
          "number": "5599",
          "score": 98.95
        },
        {
          "rank": 4,
          "number": "9555",
          "score": 98.42
        },
        {
          "rank": 5,
          "number": "4444",
          "score": 97.89
        },
        {
          "rank": 6,
          "number": "5555",
          "score": 97.37
        },
        {
          "rank": 7,
          "number": "9997",
          "score": 96.84
        },
        {
          "rank": 8,
          "number": "6444",
          "score": 96.32
        },
        {
          "rank": 9,
          "number": "9579",
          "score": 95.79
        },
        {
          "rank": 10,
          "number": "4646",
          "score": 95.26
        },
        {
          "rank": 11,
          "number": "7559",
          "score": 94.74
        },
        {
          "rank": 12,
          "number": "4844",
          "score": 94.21
        },
        {
          "rank": 13,
          "number": "6664",
          "score": 93.68
        },
        {
          "rank": 14,
          "number": "9991",
          "score": 93.16
        },
        {
          "rank": 15,
          "number": "5575",
          "score": 92.63
        },
        {
          "rank": 16,
          "number": "6484",
          "score": 92.11
        },
        {
          "rank": 17,
          "number": "6666",
          "score": 91.58
        },
        {
          "rank": 18,
          "number": "7979",
          "score": 91.05
        },
        {
          "rank": 19,
          "number": "9951",
          "score": 90.53
        },
        {
          "rank": 20,
          "number": "4044",
          "score": 90.0
        }
      ],
      "metadata": {
        "limit": 200,
        "total_predictions": 190
      }
    },
    {
      "time": "2026-03-29T06:00:05.820839+00:00",
      "time_jst": "15:00",
      "method": "even_odd_pattern",
      "top_predictions": [
        {
          "rank": 1,
          "number": "9999",
          "score": 100.0
        },
        {
          "rank": 2,
          "number": "9599",
          "score": 99.47
        },
        {
          "rank": 3,
          "number": "5995",
          "score": 98.95
        },
        {
          "rank": 4,
          "number": "5955",
          "score": 98.42
        },
        {
          "rank": 5,
          "number": "4444",
          "score": 97.89
        },
        {
          "rank": 6,
          "number": "9997",
          "score": 97.37
        },
        {
          "rank": 7,
          "number": "5555",
          "score": 96.84
        },
        {
          "rank": 8,
          "number": "4464",
          "score": 96.32
        },
        {
          "rank": 9,
          "number": "5979",
          "score": 95.79
        },
        {
          "rank": 10,
          "number": "6644",
          "score": 95.26
        },
        {
          "rank": 11,
          "number": "9557",
          "score": 94.74
        },
        {
          "rank": 12,
          "number": "4484",
          "score": 94.21
        },
        {
          "rank": 13,
          "number": "4666",
          "score": 93.68
        },
        {
          "rank": 14,
          "number": "9919",
          "score": 93.16
        },
        {
          "rank": 15,
          "number": "7555",
          "score": 92.63
        },
        {
          "rank": 16,
          "number": "4648",
          "score": 92.11
        },
        {
          "rank": 17,
          "number": "6666",
          "score": 91.58
        },
        {
          "rank": 18,
          "number": "1599",
          "score": 91.05
        },
        {
          "rank": 19,
          "number": "7997",
          "score": 90.53
        },
        {
          "rank": 20,
          "number": "0444",
          "score": 90.0
        }
      ],
      "metadata": {
        "limit": 200,
        "total_predictions": 190
      }
    },
    {
      "time": "2026-03-29T06:11:35.300608+00:00",
      "time_jst": "15:11",
      "method": "even_odd_pattern",
      "top_predictions": [
        {
          "rank": 1,
          "number": "9999",
          "score": 100.0
        },
        {
          "rank": 2,
          "number": "5999",
          "score": 99.47
        },
        {
          "rank": 3,
          "number": "5599",
          "score": 98.95
        },
        {
          "rank": 4,
          "number": "5559",
          "score": 98.42
        },
        {
          "rank": 5,
          "number": "4444",
          "score": 97.89
        },
        {
          "rank": 6,
          "number": "5555",
          "score": 97.37
        },
        {
          "rank": 7,
          "number": "9997",
          "score": 96.84
        },
        {
          "rank": 8,
          "number": "4644",
          "score": 96.32
        },
        {
          "rank": 9,
          "number": "5979",
          "score": 95.79
        },
        {
          "rank": 10,
          "number": "4646",
          "score": 95.26
        },
        {
          "rank": 11,
          "number": "5579",
          "score": 94.74
        },
        {
          "rank": 12,
          "number": "4666",
          "score": 94.21
        },
        {
          "rank": 13,
          "number": "4448",
          "score": 93.68
        },
        {
          "rank": 14,
          "number": "1999",
          "score": 93.16
        },
        {
          "rank": 15,
          "number": "5755",
          "score": 92.63
        },
        {
          "rank": 16,
          "number": "4486",
          "score": 92.11
        },
        {
          "rank": 17,
          "number": "6666",
          "score": 91.58
        },
        {
          "rank": 18,
          "number": "9159",
          "score": 91.05
        },
        {
          "rank": 19,
          "number": "9977",
          "score": 90.53
        },
        {
          "rank": 20,
          "number": "6684",
          "score": 90.0
        }
      ],
      "metadata": {
        "limit": 200,
        "total_predictions": 190
      }
    },
    {
      "time": "2026-03-29T12:54:45.139017+00:00",
      "time_jst": "21:54",
      "method": "even_odd_pattern",
      "top_predictions": [
        {
          "rank": 1,
          "number": "9999",
          "score": 100.0
        },
        {
          "rank": 2,
          "number": "5999",
          "score": 99.47
        },
        {
          "rank": 3,
          "number": "9955",
          "score": 98.95
        },
        {
          "rank": 4,
          "number": "5595",
          "score": 98.42
        },
        {
          "rank": 5,
          "number": "4444",
          "score": 97.89
        },
        {
          "rank": 6,
          "number": "9997",
          "score": 97.37
        },
        {
          "rank": 7,
          "number": "5555",
          "score": 96.84
        },
        {
          "rank": 8,
          "number": "4644",
          "score": 96.32
        },
        {
          "rank": 9,
          "number": "5979",
          "score": 95.79
        },
        {
          "rank": 10,
          "number": "6446",
          "score": 95.26
        },
        {
          "rank": 11,
          "number": "5975",
          "score": 94.74
        },
        {
          "rank": 12,
          "number": "4448",
          "score": 94.21
        },
        {
          "rank": 13,
          "number": "6646",
          "score": 93.68
        },
        {
          "rank": 14,
          "number": "9199",
          "score": 93.16
        },
        {
          "rank": 15,
          "number": "5575",
          "score": 92.63
        },
        {
          "rank": 16,
          "number": "4864",
          "score": 92.11
        },
        {
          "rank": 17,
          "number": "6666",
          "score": 91.58
        },
        {
          "rank": 18,
          "number": "9779",
          "score": 91.05
        },
        {
          "rank": 19,
          "number": "9951",
          "score": 90.53
        },
        {
          "rank": 20,
          "number": "8646",
          "score": 90.0
        }
      ],
      "metadata": {
        "limit": 200,
        "total_predictions": 190
      }
    },
    {
      "time": "2026-03-29T18:07:21.225612+00:00",
      "time_jst": "03:07",
      "method": "even_odd_pattern",
      "top_predictions": [
        {
          "rank": 1,
          "number": "9999",
          "score": 100.0
        },
        {
          "rank": 2,
          "number": "9959",
          "score": 99.47
        },
        {
          "rank": 3,
          "number": "5995",
          "score": 98.95
        },
        {
          "rank": 4,
          "number": "5595",
          "score": 98.42
        },
        {
          "rank": 5,
          "number": "4444",
          "score": 97.89
        },
        {
          "rank": 6,
          "number": "7999",
          "score": 97.37
        },
        {
          "rank": 7,
          "number": "5555",
          "score": 96.84
        },
        {
          "rank": 8,
          "number": "4446",
          "score": 96.32
        },
        {
          "rank": 9,
          "number": "5799",
          "score": 95.79
        },
        {
          "rank": 10,
          "number": "4466",
          "score": 95.26
        },
        {
          "rank": 11,
          "number": "5957",
          "score": 94.74
        },
        {
          "rank": 12,
          "number": "4484",
          "score": 94.21
        },
        {
          "rank": 13,
          "number": "6646",
          "score": 93.68
        },
        {
          "rank": 14,
          "number": "9199",
          "score": 93.16
        },
        {
          "rank": 15,
          "number": "5575",
          "score": 92.63
        },
        {
          "rank": 16,
          "number": "6484",
          "score": 92.11
        },
        {
          "rank": 17,
          "number": "6666",
          "score": 91.58
        },
        {
          "rank": 18,
          "number": "1599",
          "score": 91.05
        },
        {
          "rank": 19,
          "number": "7799",
          "score": 90.53
        },
        {
          "rank": 20,
          "number": "8664",
          "score": 90.0
        }
      ],
      "metadata": {
        "limit": 200,
        "total_predictions": 190
      }
    },
    {
      "time": "2026-03-29T19:41:04.407678+00:00",
      "time_jst": "04:41",
      "method": "even_odd_pattern",
      "top_predictions": [
        {
          "rank": 1,
          "number": "9999",
          "score": 100.0
        },
        {
          "rank": 2,
          "number": "9599",
          "score": 99.47
        },
        {
          "rank": 3,
          "number": "9559",
          "score": 98.95
        },
        {
          "rank": 4,
          "number": "9555",
          "score": 98.42
        },
        {
          "rank": 5,
          "number": "4444",
          "score": 97.89
        },
        {
          "rank": 6,
          "number": "5555",
          "score": 97.37
        },
        {
          "rank": 7,
          "number": "9979",
          "score": 96.84
        },
        {
          "rank": 8,
          "number": "4644",
          "score": 96.32
        },
        {
          "rank": 9,
          "number": "7959",
          "score": 95.79
        },
        {
          "rank": 10,
          "number": "6464",
          "score": 95.26
        },
        {
          "rank": 11,
          "number": "5759",
          "score": 94.74
        },
        {
          "rank": 12,
          "number": "6646",
          "score": 94.21
        },
        {
          "rank": 13,
          "number": "8444",
          "score": 93.68
        },
        {
          "rank": 14,
          "number": "5557",
          "score": 93.16
        },
        {
          "rank": 15,
          "number": "1999",
          "score": 92.63
        },
        {
          "rank": 16,
          "number": "4468",
          "score": 92.11
        },
        {
          "rank": 17,
          "number": "6666",
          "score": 91.58
        },
        {
          "rank": 18,
          "number": "1959",
          "score": 91.05
        },
        {
          "rank": 19,
          "number": "7979",
          "score": 90.53
        },
        {
          "rank": 20,
          "number": "6648",
          "score": 90.0
        }
      ],
      "metadata": {
        "limit": 200,
        "total_predictions": 190
      }
    },
    {
      "time": "2026-03-29T21:05:44.403404+00:00",
      "time_jst": "06:05",
      "method": "even_odd_pattern",
      "top_predictions": [
        {
          "rank": 1,
          "number": "9999",
          "score": 100.0
        },
        {
          "rank": 2,
          "number": "9995",
          "score": 99.47
        },
        {
          "rank": 3,
          "number": "5995",
          "score": 98.95
        },
        {
          "rank": 4,
          "number": "5955",
          "score": 98.42
        },
        {
          "rank": 5,
          "number": "4444",
          "score": 97.89
        },
        {
          "rank": 6,
          "number": "9997",
          "score": 97.37
        },
        {
          "rank": 7,
          "number": "5555",
          "score": 96.84
        },
        {
          "rank": 8,
          "number": "6444",
          "score": 96.32
        },
        {
          "rank": 9,
          "number": "9957",
          "score": 95.79
        },
        {
          "rank": 10,
          "number": "6644",
          "score": 95.26
        },
        {
          "rank": 11,
          "number": "5597",
          "score": 94.74
        },
        {
          "rank": 12,
          "number": "6664",
          "score": 94.21
        },
        {
          "rank": 13,
          "number": "4448",
          "score": 93.68
        },
        {
          "rank": 14,
          "number": "5755",
          "score": 93.16
        },
        {
          "rank": 15,
          "number": "9199",
          "score": 92.63
        },
        {
          "rank": 16,
          "number": "6844",
          "score": 92.11
        },
        {
          "rank": 17,
          "number": "6666",
          "score": 91.58
        },
        {
          "rank": 18,
          "number": "9915",
          "score": 91.05
        },
        {
          "rank": 19,
          "number": "9797",
          "score": 90.53
        },
        {
          "rank": 20,
          "number": "8466",
          "score": 90.0
        }
      ],
      "metadata": {
        "limit": 200,
        "total_predictions": 190
      }
    }
  ],
  "last_updated": "2026-03-29T21:05:44.403404+00:00",
  "prediction_count": 8
}