{
  "draw_number": 6939,
  "target_draw_number": 6939,
  "date": "20260312",
  "method": "lightgbm",
  "predictions": [
    {
      "time": "2026-03-12T19:15:39.483572+00:00",
      "time_jst": "04:15",
      "method": "lightgbm",
      "top_predictions": [],
      "metadata": {
        "limit": 200,
        "total_predictions": 0
      }
    },
    {
      "time": "2026-03-12T20:43:15.647610+00:00",
      "time_jst": "05:43",
      "method": "lightgbm",
      "top_predictions": [],
      "metadata": {
        "limit": 200,
        "total_predictions": 0
      }
    }
  ],
  "last_updated": "2026-03-12T20:43:15.647610+00:00",
  "prediction_count": 2
}